[
  {
    "internal": [
      "some internal comments here"
    ],
    "authors": {
      "main": "123",
      "more": ["456", "789"]
    },
    "dates": {
      "created": "2020-01-04",
      "published": "2020-01-05",
      "updated": "2020-01-06",
      "expiry": "2030-12-31"
    },
    "descriptions": {
      "long": "This is a long description.",
      "short": "This is a short description."
    },
    "identifications": {
      "alias": ["Alias 3", "Alias 4"],
      "ksid": "v-789-012",
      "name": "Verse 2"
    },
    "images": {
      "landscape": ["https://img.youronly.one"],
      "portrait": ["https://img.youronly.one"],
      "square": ["https://img.youronly.one"]
    },
    "content": "This is a `.Content` with markdown support."
  }
]
